[
  {
    "name": "employees",
    "path": "/employees",
    "component": "/app/nuxt-project/pages/employees/index.vue",
    "chunkName": "pages/employees/index",
    "_name": "_5f70c93c"
  },
  {
    "name": "food_products",
    "path": "/food_products",
    "component": "/app/nuxt-project/pages/food_products/index.vue",
    "chunkName": "pages/food_products/index",
    "_name": "_2b0ac3dc"
  },
  {
    "name": "groups",
    "path": "/groups",
    "component": "/app/nuxt-project/pages/groups/index.vue",
    "chunkName": "pages/groups/index",
    "_name": "_18c34093"
  },
  {
    "name": "inspire",
    "path": "/inspire",
    "component": "/app/nuxt-project/pages/inspire.vue",
    "chunkName": "pages/inspire",
    "_name": "_7f52cd64"
  },
  {
    "name": "mypage",
    "path": "/mypage",
    "component": "/app/nuxt-project/pages/mypage.vue",
    "chunkName": "pages/mypage",
    "_name": "_6faa4a12"
  },
  {
    "name": "place_orders",
    "path": "/place_orders",
    "component": "/app/nuxt-project/pages/place_orders/index.vue",
    "chunkName": "pages/place_orders/index",
    "_name": "_1eaf94c8"
  },
  {
    "name": "power",
    "path": "/power",
    "component": "/app/nuxt-project/pages/power.vue",
    "chunkName": "pages/power",
    "_name": "_176bae0e"
  },
  {
    "name": "power_orders",
    "path": "/power_orders",
    "component": "/app/nuxt-project/pages/power_orders/index.vue",
    "chunkName": "pages/power_orders/index",
    "_name": "_d5ce7d44"
  },
  {
    "name": "project_names",
    "path": "/project_names",
    "component": "/app/nuxt-project/pages/project_names/index.vue",
    "chunkName": "pages/project_names/index",
    "_name": "_2c169a19"
  },
  {
    "name": "purchase_lists",
    "path": "/purchase_lists",
    "component": "/app/nuxt-project/pages/purchase_lists/index.vue",
    "chunkName": "pages/purchase_lists/index",
    "_name": "_2fb4bc54"
  },
  {
    "name": "regist_user_detail",
    "path": "/regist_user_detail",
    "component": "/app/nuxt-project/pages/regist_user_detail.vue",
    "chunkName": "pages/regist_user_detail",
    "_name": "_2aa33390"
  },
  {
    "name": "rental_items",
    "path": "/rental_items",
    "component": "/app/nuxt-project/pages/rental_items/index.vue",
    "chunkName": "pages/rental_items/index",
    "_name": "_66145138"
  },
  {
    "name": "rental_orders",
    "path": "/rental_orders",
    "component": "/app/nuxt-project/pages/rental_orders/index.vue",
    "chunkName": "pages/rental_orders/index",
    "_name": "_16030857"
  },
  {
    "name": "signup",
    "path": "/signup",
    "component": "/app/nuxt-project/pages/signup.vue",
    "chunkName": "pages/signup",
    "_name": "_5ee1db54"
  },
  {
    "name": "stage_orders",
    "path": "/stage_orders",
    "component": "/app/nuxt-project/pages/stage_orders/index.vue",
    "chunkName": "pages/stage_orders/index",
    "_name": "_1faa9885"
  },
  {
    "name": "sub_reps",
    "path": "/sub_reps",
    "component": "/app/nuxt-project/pages/sub_reps/index.vue",
    "chunkName": "pages/sub_reps/index",
    "_name": "_18296e94"
  },
  {
    "name": "users",
    "path": "/users",
    "component": "/app/nuxt-project/pages/users/index.vue",
    "chunkName": "pages/users/index",
    "_name": "_123c2dff"
  },
  {
    "name": "users-print",
    "path": "/users/print",
    "component": "/app/nuxt-project/pages/users/print/index.vue",
    "chunkName": "pages/users/print/index",
    "_name": "_497a2d5d"
  },
  {
    "name": "employees-id",
    "path": "/employees/:id",
    "component": "/app/nuxt-project/pages/employees/_id.vue",
    "chunkName": "pages/employees/_id",
    "_name": "_45d7eaa4"
  },
  {
    "name": "food_products-id",
    "path": "/food_products/:id",
    "component": "/app/nuxt-project/pages/food_products/_id.vue",
    "chunkName": "pages/food_products/_id",
    "_name": "_121fe578"
  },
  {
    "name": "groups-id",
    "path": "/groups/:id",
    "component": "/app/nuxt-project/pages/groups/_id.vue",
    "chunkName": "pages/groups/_id",
    "_name": "_8183688a"
  },
  {
    "name": "place_orders-id",
    "path": "/place_orders/:id",
    "component": "/app/nuxt-project/pages/place_orders/_id.vue",
    "chunkName": "pages/place_orders/_id",
    "_name": "_168221f8"
  },
  {
    "name": "power_orders-id",
    "path": "/power_orders/:id",
    "component": "/app/nuxt-project/pages/power_orders/_id.vue",
    "chunkName": "pages/power_orders/_id",
    "_name": "_58038346"
  },
  {
    "name": "project_names-id",
    "path": "/project_names/:id",
    "component": "/app/nuxt-project/pages/project_names/_id.vue",
    "chunkName": "pages/project_names/_id",
    "_name": "_04864ec1"
  },
  {
    "name": "purchase_lists-id",
    "path": "/purchase_lists/:id",
    "component": "/app/nuxt-project/pages/purchase_lists/_id.vue",
    "chunkName": "pages/purchase_lists/_id",
    "_name": "_e183bc84"
  },
  {
    "name": "rental_items-id",
    "path": "/rental_items/:id",
    "component": "/app/nuxt-project/pages/rental_items/_id.vue",
    "chunkName": "pages/rental_items/_id",
    "_name": "_8bcb3a68"
  },
  {
    "name": "rental_orders-id",
    "path": "/rental_orders/:id",
    "component": "/app/nuxt-project/pages/rental_orders/_id.vue",
    "chunkName": "pages/rental_orders/_id",
    "_name": "_3695347f"
  },
  {
    "name": "stage_orders-id",
    "path": "/stage_orders/:id",
    "component": "/app/nuxt-project/pages/stage_orders/_id.vue",
    "chunkName": "pages/stage_orders/_id",
    "_name": "_5b9ef82d"
  },
  {
    "name": "sub_reps-id",
    "path": "/sub_reps/:id",
    "component": "/app/nuxt-project/pages/sub_reps/_id.vue",
    "chunkName": "pages/sub_reps/_id",
    "_name": "_2aabf408"
  },
  {
    "name": "users-id",
    "path": "/users/:id",
    "component": "/app/nuxt-project/pages/users/_id.vue",
    "chunkName": "pages/users/_id",
    "_name": "_42a8b7b2"
  },
  {
    "name": "index",
    "path": "/",
    "component": "/app/nuxt-project/pages/index.vue",
    "chunkName": "pages/index",
    "_name": "_dc6fcb74"
  }
]
